{
 "finalResult": [
  {
   "amount": 82.74,
   "from": "EQCoGwWMDG8AxtXiMaUybUtEbS4s46OVDuMvP8x6pPKpiQla",
   "time": "2022-05-21 09:47:25 +0800 CST",
   "to": "Bridge Oracle 6"
  },
  {
   "amount": 82.74,
   "from": "EQCoGwWMDG8AxtXiMaUybUtEbS4s46OVDuMvP8x6pPKpiQla",
   "time": "2022-05-21 09:47:25 +0800 CST",
   "to": "Bridge Oracle 4"
  },
  {
   "amount": 191.537,
   "from": "EQDHoQEq0HGFwxIRgtMWfAfiQv-6WYmc37fWM6EpSxdmVIf7",
   "time": "2022-05-21 09:44:03 +0800 CST",
   "to": "OKX"
  }
 ],
 "notice": []
}